pipefy/__init__.py
pipefy/etl/__init__.py
pipefy/etl/extract/__init__.py
pipefy/etl/extract/http/__init__.py
pipefy/etl/extract/http/http_extractor.py
pipefy/etl/transform/__init__.py
pipefy/etl/transform/csv/__init__.py
pipefy/etl/transform/csv/reader.py
pipefy/etl/transform/json/__init__.py
pipefy/etl/transform/json/reader.py
pipefy/etl/transform/unzip/__init__.py
pipefy/etl/transform/unzip/base.py
pipefy/exceptions/__init__.py
pipefy/exceptions/base.py
pipefy/exceptions/csv_processor.py
pipefy/exceptions/download_processor.py
pipefy/exceptions/file_system.py
pipefy/exceptions/unzip_processor.py
pipefy/factories/__init__.py
pipefy/factories/exceptions_factory.py
pipefy/factories/file_system_factory.py
pipefy/log/__init__.py
pipefy/log/logger.py
pipefy/operations/__init__.py
pipefy/operations/operations.py
pipefy/operations/pipeline.py
pipefy/processors/__init__.py
pipefy/processors/abc.py
pipefy/processors/base.py
pipefy/processors/chain_processors/__init__.py
pipefy/processors/chain_processors/base.py
pipefy/processors/file_system/__init__.py
pipefy/processors/file_system/base.py
pipefy/processors/file_system/file_system_types.py
pipefy/processors/meta.py
pipefy/processors/mixins.py
pipefy/processors/processor_types.py
pipefy/processors/retry_processor.py
pipefy/processors/splitter_processor.py
pipefy/utils/__init__.py
pipefy/utils/common.py
pipefy-1.0.0.dist-info/LICENSE
pipefy-1.0.0.dist-info/METADATA
pipefy-1.0.0.dist-info/WHEEL
pipefy-1.0.0.dist-info/RECORD
